yandex_search/__init__.py
yandex_search/example.py
yandex_search-0.3.2.dist-info/DESCRIPTION.rst
yandex_search-0.3.2.dist-info/METADATA
yandex_search-0.3.2.dist-info/RECORD
yandex_search-0.3.2.dist-info/WHEEL
yandex_search-0.3.2.dist-info/metadata.json
yandex_search-0.3.2.dist-info/top_level.txt
