Metadata-Version: 1.1
Name: yandex-search
Version: 0.3.2
Summary: Yandex search library
Home-page: https://github.com/codinguncut/yandex-search
Author: Johannes Ahlmann
Author-email: johannes@fluquid.com
License: MIT
Keywords: yandex-search
Platform: UNKNOWN
Classifier: Development Status :: 2 - Pre-Alpha
Classifier: Intended Audience :: Developers
Classifier: License :: OSI Approved :: MIT License
Classifier: Natural Language :: English
Classifier: Programming Language :: Python :: 2
Classifier: Programming Language :: Python :: 2.7
Classifier: Programming Language :: Python :: 3
Classifier: Programming Language :: Python :: 3.4
Classifier: Programming Language :: Python :: 3.5
